{
  "main": {
    "id": "0fa75fd878af18b2",
    "type": "split",
    "children": [
      {
        "id": "56c1a37c7a07ee1e",
        "type": "tabs",
        "children": [
          {
            "id": "2e138c036e8798b0",
            "type": "leaf",
            "state": {
              "type": "graph",
              "state": {},
              "icon": "lucide-git-fork",
              "title": "Graph view"
            }
          },
          {
            "id": "a32e230cd5771764",
            "type": "leaf",
            "state": {
              "type": "markdown",
              "state": {
                "file": "Programming Languages/C Sharp.md",
                "mode": "source",
                "source": false
              },
              "icon": "lucide-file",
              "title": "C Sharp"
            }
          },
          {
            "id": "e5792a77992b306d",
            "type": "leaf",
            "state": {
              "type": "canvas",
              "state": {
                "file": "Mindmap.canvas",
                "viewState": {
                  "x": -297.5,
                  "y": 244.5,
                  "zoom": 0
                }
              },
              "icon": "lucide-layout-dashboard",
              "title": "Mindmap"
            }
          },
          {
            "id": "f2414465e4954e57",
            "type": "leaf",
            "state": {
              "type": "markdown",
              "state": {
                "file": "Endpoints.md",
                "mode": "source",
                "source": false
              },
              "icon": "lucide-file",
              "title": "Endpoints"
            }
          },
          {
            "id": "36f58995081a1249",
            "type": "leaf",
            "state": {
              "type": "markdown",
              "state": {
                "file": "Microsoft Framworks/ASP NET.md",
                "mode": "source",
                "source": false
              },
              "icon": "lucide-file",
              "title": "ASP NET"
            }
          },
          {
            "id": "fcbcd0b26d1cdd5f",
            "type": "leaf",
            "state": {
              "type": "markdown",
              "state": {
                "file": "Microsoft Framworks/ADO NET.md",
                "mode": "source",
                "source": false
              },
              "icon": "lucide-file",
              "title": "ADO NET"
            }
          },
          {
            "id": "20c6b2461b642d61",
            "type": "leaf",
            "state": {
              "type": "markdown",
              "state": {
                "file": "Web Development/JWT.md",
                "mode": "source",
                "source": false
              },
              "icon": "lucide-file",
              "title": "JWT"
            }
          },
          {
            "id": "6264f595015bd3d7",
            "type": "leaf",
            "state": {
              "type": "markdown",
              "state": {
                "file": "System Architecture/System Architecture.md",
                "mode": "source",
                "source": false
              },
              "icon": "lucide-file",
              "title": "System Architecture"
            }
          },
          {
            "id": "964c92805cbff135",
            "type": "leaf",
            "state": {
              "type": "markdown",
              "state": {
                "file": "Techniques/Dependency Injection.md",
                "mode": "source",
                "source": false
              },
              "icon": "lucide-file",
              "title": "Dependency Injection"
            }
          },
          {
            "id": "92b4f845f1a44d0f",
            "type": "leaf",
            "state": {
              "type": "markdown",
              "state": {
                "file": "APIs/Web API.md",
                "mode": "source",
                "source": false
              },
              "icon": "lucide-file",
              "title": "Web API"
            }
          }
        ]
      }
    ],
    "direction": "vertical"
  },
  "left": {
    "id": "ac6aee80ba0599eb",
    "type": "split",
    "children": [
      {
        "id": "960bafe7a29d5d47",
        "type": "tabs",
        "children": [
          {
            "id": "1636a5ef8764db43",
            "type": "leaf",
            "state": {
              "type": "file-explorer",
              "state": {
                "sortOrder": "alphabetical",
                "autoReveal": false
              },
              "icon": "lucide-folder-closed",
              "title": "Files"
            }
          },
          {
            "id": "95a51cf890edc50e",
            "type": "leaf",
            "state": {
              "type": "search",
              "state": {
                "query": "",
                "matchingCase": false,
                "explainSearch": false,
                "collapseAll": false,
                "extraContext": false,
                "sortOrder": "alphabetical"
              },
              "icon": "lucide-search",
              "title": "Search"
            }
          },
          {
            "id": "a0ab809c6cfd3939",
            "type": "leaf",
            "state": {
              "type": "bookmarks",
              "state": {},
              "icon": "lucide-bookmark",
              "title": "Bookmarks"
            }
          }
        ]
      }
    ],
    "direction": "horizontal",
    "width": 300
  },
  "right": {
    "id": "13e4b83a11522335",
    "type": "split",
    "children": [
      {
        "id": "8608d4d9f6a699a2",
        "type": "tabs",
        "children": [
          {
            "id": "ee7fdf58afcae6a3",
            "type": "leaf",
            "state": {
              "type": "backlink",
              "state": {
                "file": "Untitled.canvas",
                "collapseAll": false,
                "extraContext": false,
                "sortOrder": "alphabetical",
                "showSearch": false,
                "searchQuery": "",
                "backlinkCollapsed": false,
                "unlinkedCollapsed": true
              },
              "icon": "links-coming-in",
              "title": "Backlinks for Untitled"
            }
          },
          {
            "id": "72618bf08ad9122c",
            "type": "leaf",
            "state": {
              "type": "outgoing-link",
              "state": {
                "file": "Untitled.canvas",
                "linksCollapsed": false,
                "unlinkedCollapsed": true
              },
              "icon": "links-going-out",
              "title": "Outgoing links from Untitled"
            }
          },
          {
            "id": "87a8418d52d57d68",
            "type": "leaf",
            "state": {
              "type": "tag",
              "state": {
                "sortOrder": "frequency",
                "useHierarchy": true,
                "showSearch": false,
                "searchQuery": ""
              },
              "icon": "lucide-tags",
              "title": "Tags"
            }
          },
          {
            "id": "af937fcb569f939d",
            "type": "leaf",
            "state": {
              "type": "all-properties",
              "state": {
                "sortOrder": "frequency",
                "showSearch": false,
                "searchQuery": ""
              },
              "icon": "lucide-archive",
              "title": "All properties"
            }
          },
          {
            "id": "3cacbe753ad2f479",
            "type": "leaf",
            "state": {
              "type": "outline",
              "state": {
                "file": "Untitled.canvas",
                "followCursor": false,
                "showSearch": false,
                "searchQuery": ""
              },
              "icon": "lucide-list",
              "title": "Outline of Untitled"
            }
          }
        ]
      }
    ],
    "direction": "horizontal",
    "width": 300,
    "collapsed": true
  },
  "left-ribbon": {
    "hiddenItems": {
      "switcher:Open quick switcher": false,
      "graph:Open graph view": false,
      "canvas:Create new canvas": false,
      "daily-notes:Open today's daily note": false,
      "templates:Insert template": false,
      "command-palette:Open command palette": false,
      "bases:Create new base": false,
      "table-editor-obsidian:Advanced Tables Toolbar": false
    }
  },
  "active": "2e138c036e8798b0",
  "lastOpenFiles": [
    "Microsoft Framworks/xUnit.md",
    "Production/Unit Testing.md",
    "Databases/Databases.md",
    "Databases/Database Types Mindmap.canvas",
    "System Architecture/System Architecture.md",
    "Microsoft Framworks/LINQ.md",
    "Production/CI CD.md",
    "Production/Docker.md",
    "Programming Languages/C Sharp.md",
    "System Architecture/Object Oriented.md",
    "Production/Kubernetes.md",
    "Production/Container.md",
    "Images/Pasted image 20260603110027.png",
    "Images",
    "Images/Pasted image 20260701114330.png",
    "Images/Pasted image 20260701112629.png",
    "Production",
    "APIs/Versioning.md",
    "Programming Languages/JavaScript.md",
    "Techniques/Data Transfer Objects.md",
    "Techniques/Dependency Injection.md",
    "Web Development/Dynamic Websites.md",
    "Web Development/Security.md",
    "Web Development/JWT.md",
    "Images/Pasted image 20260624105306.png",
    "System Architecture",
    "Images/Pasted image 20260623111507.png",
    "APIs/Web API.md",
    "Images/Pasted image 20260603155112.png",
    "Pasted image 20260611104033.png",
    "Web Development/Endpoints.md",
    "Microsoft Framworks/Entity Framework Core.md",
    "Microsoft Framworks/ADO NET.md",
    "Web Development/Static Websites.md",
    "Web Development/Web Development.md",
    "Microsoft Framworks/ASP NET.md",
    "APIs/API.md",
    "Techniques",
    "Programming Obsidian Vault",
    "APIs",
    "Web Development",
    "Databases",
    "Microsoft Framworks",
    "Programming Languages"
  ]
}